singleton_decorator-stubs/__init__.pyi
singleton_decorator-stubs/py.typed
types_singleton_decorator-0.1.0.dist-info/METADATA
types_singleton_decorator-0.1.0.dist-info/WHEEL
types_singleton_decorator-0.1.0.dist-info/licenses/LICENSE
types_singleton_decorator-0.1.0.dist-info/RECORD
