Metadata-Version: 2.4
Name: types-singleton-decorator
Version: 0.1.0
Summary: Type stubs for singleton_decorator
Project-URL: Homepage, https://github.com/rohitshubham/types-singleton-decorator
Project-URL: Repository, https://github.com/rohitshubham/types-singleton-decorator
Project-URL: Issues, https://github.com/rohitshubham/types-singleton-decorator/issues
Author: Rohit Raj
License: MIT
License-File: LICENSE
Keywords: decorator,singleton,stubs,typing
Classifier: Development Status :: 4 - Beta
Classifier: Intended Audience :: Developers
Classifier: License :: OSI Approved :: MIT License
Classifier: Programming Language :: Python :: 3
Classifier: Programming Language :: Python :: 3.8
Classifier: Programming Language :: Python :: 3.9
Classifier: Programming Language :: Python :: 3.10
Classifier: Programming Language :: Python :: 3.11
Classifier: Programming Language :: Python :: 3.12
Classifier: Typing :: Typed
Requires-Python: >=3.8
